cutout/__init__.py
cutout/survey/__init__.py
cutout/survey/survey.py
cutout/tools/__init__.py
cutout/tools/tools.py
cutout-0.3.1.dist-info/LICENSE
cutout-0.3.1.dist-info/METADATA
cutout-0.3.1.dist-info/WHEEL
cutout-0.3.1.dist-info/top_level.txt
cutout-0.3.1.dist-info/RECORD
